setup.py
tudejian_test_pypi/__init__.py
tudejian_test_pypi.egg-info/PKG-INFO
tudejian_test_pypi.egg-info/SOURCES.txt
tudejian_test_pypi.egg-info/dependency_links.txt
tudejian_test_pypi.egg-info/entry_points.txt
tudejian_test_pypi.egg-info/top_level.txt