Metadata-Version: 1.0
Name: tudejian-test-pypi
Version: 0.0.1
Summary: Test pipy upload by tudejian
Home-page: UNKNOWN
Author: tudejian
Author-email: tudejian@gmail.com
License: UNKNOWN
Platform: UNKNOWN
